nominatim_api/__init__.py
nominatim_api/connection.py
nominatim_api/core.py
nominatim_api/errors.py
nominatim_api/localization.py
nominatim_api/logging.py
nominatim_api/lookup.py
nominatim_api/py.typed
nominatim_api/result_formatting.py
nominatim_api/results.py
nominatim_api/reverse.py
nominatim_api/status.py
nominatim_api/types.py
nominatim_api/typing.py
nominatim_api/version.py
nominatim_api/query_preprocessing/__init__.py
nominatim_api/query_preprocessing/base.py
nominatim_api/query_preprocessing/config.py
nominatim_api/query_preprocessing/normalize.py
nominatim_api/query_preprocessing/split_japanese_phrases.py
nominatim_api/search/__init__.py
nominatim_api/search/db_search_builder.py
nominatim_api/search/db_search_fields.py
nominatim_api/search/db_search_lookups.py
nominatim_api/search/db_searches.py
nominatim_api/search/geocoder.py
nominatim_api/search/icu_tokenizer.py
nominatim_api/search/postcode_parser.py
nominatim_api/search/query.py
nominatim_api/search/query_analyzer_factory.py
nominatim_api/search/token_assignment.py
nominatim_api/server/__init__.py
nominatim_api/server/asgi_adaptor.py
nominatim_api/server/content_types.py
nominatim_api/server/falcon/__init__.py
nominatim_api/server/falcon/server.py
nominatim_api/server/starlette/__init__.py
nominatim_api/server/starlette/server.py
nominatim_api/sql/__init__.py
nominatim_api/sql/async_core_library.py
nominatim_api/sql/sqlalchemy_functions.py
nominatim_api/sql/sqlalchemy_schema.py
nominatim_api/sql/sqlite_functions.py
nominatim_api/sql/sqlalchemy_types/__init__.py
nominatim_api/sql/sqlalchemy_types/geometry.py
nominatim_api/sql/sqlalchemy_types/int_array.py
nominatim_api/sql/sqlalchemy_types/json.py
nominatim_api/sql/sqlalchemy_types/key_value.py
nominatim_api/utils/__init__.py
nominatim_api/utils/json_writer.py
nominatim_api/v1/__init__.py
nominatim_api/v1/classtypes.py
nominatim_api/v1/format.py
nominatim_api/v1/format_json.py
nominatim_api/v1/format_xml.py
nominatim_api/v1/helpers.py
nominatim_api-5.1.0.dist-info/METADATA
nominatim_api-5.1.0.dist-info/WHEEL
nominatim_api-5.1.0.dist-info/RECORD
