Metadata-Version: 2.4
Name: nominatim-api
Version: 5.1.0
Summary: A tool for building a database of OpenStreetMap for geocoding and for searching the database. Search library.
Project-URL: Homepage, https://nominatim.org
Project-URL: Documentation, https://nominatim.org/release-docs/latest/
Project-URL: Issues, https://github.com/osm-search/Nominatim/issues
Project-URL: Repository, https://github.com/osm-search/Nominatim
Maintainer-email: Sarah Hoffmann <lonvia@denofr.de>, Marc Tobias <mtmail-cpan@gmx.net>
License-Expression: GPL-3.0-or-later
Keywords: OpenStreetMap,geocoding,search
Classifier: License :: OSI Approved :: GNU General Public License (GPL)
Classifier: Operating System :: OS Independent
Classifier: Programming Language :: Python :: 3
Requires-Python: >=3.7
Requires-Dist: psycopg
Requires-Dist: pyicu
Requires-Dist: python-dotenv
Requires-Dist: pyyaml>=5.1
Requires-Dist: sqlalchemy>=1.4.31
